README.rst
flask_dotenv.py
setup.py
Flask_DotEnv.egg-info/PKG-INFO
Flask_DotEnv.egg-info/SOURCES.txt
Flask_DotEnv.egg-info/dependency_links.txt
Flask_DotEnv.egg-info/not-zip-safe
Flask_DotEnv.egg-info/requires.txt
Flask_DotEnv.egg-info/top_level.txt