Metadata-Version: 1.1
Name: Flask-DotEnv
Version: 0.0.3
Summary: The .env file support for Flask
Home-page: https://github.com/grauwoelfchen/flask-dotenv/
Author: Yasuhiro Asaka
Author-email: grauwoelfchen@gmail.com
License: BSD
Platform: any
Classifier: Development Status :: 4 - Beta
Classifier: Environment :: Web Environment
Classifier: Intended Audience :: Developers
Classifier: License :: OSI Approved :: BSD License
Classifier: Operating System :: OS Independent
Classifier: Programming Language :: Python
Classifier: Topic :: Internet :: WWW/HTTP :: Dynamic Content
Classifier: Topic :: Software Development :: Libraries :: Python Modules
